<?xml version="1.0" encoding="UTF-8"?>
<objects serializationModel="Studio.02.02.00">
	<object class="EncodingSetting" id="{b46d51aa-f95e-4d1d-8b51-8c8333c3e6db}">
		<property name="encodingFormat">
			<value>3</value>
		</property>
		<property name="quality">
			<value>37</value>
		</property>
		<relationship name="platform">
			<destination>{7130b107-a453-4da1-9df3-94891ae065f7}</destination>
		</relationship>
		<relationship name="encodable">
			<destination>{7130b107-a453-4da1-9df3-94891ae065f7}</destination>
		</relationship>
	</object>
</objects>
